dlsite_recommendation_llm/__init__.py
dlsite_recommendation_llm/cli.py
dlsite_recommendation_llm/main.py
dlsite_recommendation_llm/static_files/favicon.png
dlsite_recommendation_llm-0.0.0.dist-info/LICENSE
dlsite_recommendation_llm-0.0.0.dist-info/METADATA
dlsite_recommendation_llm-0.0.0.dist-info/WHEEL
dlsite_recommendation_llm-0.0.0.dist-info/entry_points.txt
dlsite_recommendation_llm-0.0.0.dist-info/RECORD
