Metadata-Version: 2.1
Name: dlsite_recommendation_llm
Version: 0.0.0
Summary: Recommend DLSite voice works with LLM
Home-page: https://github.com/eggplants/dlsite-recommendation-llm
License: MIT
Keywords: llm,dlsite
Author: eggplants
Author-email: w10776e8w@yahoo.co.jp
Requires-Python: >3.9.7,<3.13
Classifier: Development Status :: 3 - Alpha
Classifier: License :: OSI Approved :: MIT License
Classifier: Programming Language :: Python :: 3
Classifier: Programming Language :: Python :: 3.10
Classifier: Programming Language :: Python :: 3.11
Classifier: Programming Language :: Python :: 3.12
Classifier: Programming Language :: Python :: 3 :: Only
Requires-Dist: langchain (>=0.1.6,<0.2.0)
Requires-Dist: langchain-community (>=0.0.19,<0.0.20)
Requires-Dist: langchain-openai (>=0.0.5,<0.0.6)
Requires-Dist: pinecone-client (>=3.0.2,<4.0.0)
Requires-Dist: python-dotenv (>=1.0.1,<2.0.0)
Requires-Dist: streamlit (>=1.31.1,<2.0.0)
Project-URL: Repository, https://github.com/eggplants/dlsite-recommendation-llm
